lambdatadwight/__init__.py
lamdadatadwightc-0.0.2.dist-info/METADATA
lamdadatadwightc-0.0.2.dist-info/WHEEL
lamdadatadwightc-0.0.2.dist-info/top_level.txt
lamdadatadwightc-0.0.2.dist-info/RECORD
